[
  {
    "Date": "2019-12-30",
    "Country": "US",
    "City": "Los Angeles",
    "Specie": "pm25",
    "count": 48,
    "min": 5,
    "max": 83,
    "median": 42,
    "variance": 3699.78
  },
  {
    "Date": "2019-12-31",
    "Country": "US",
    "City": "Los Angeles",
    "Specie": "pm25",
    "count": 46,
    "min": 2,
    "max": 157,
    "median": 51,
    "variance": 10593.9
  },
  {
    "Date": "2020-01-01",
    "Country": "US",
    "City": "Los Angeles",
    "Specie": "pm25",
    "count": 48,
    "min": 21,
    "max": 175,
    "median": 61,
    "variance": 16928.9
  },
  {
    "Date": "2020-01-02",
    "Country": "US",
    "City": "Los Angeles",
    "Specie": "pm25",
    "count": 118,
    "min": 30,
    "max": 85,
    "median": 61,
    "variance": 1679.41
  },
  {
    "Date": "2020-01-03",
    "Country": "US",
    "City": "Los Angeles",
    "Specie": "pm25",
    "count": 120,
    "min": 30,
    "max": 105,
    "median": 63,
    "variance": 3248.23
  },
  {
    "Date": "2020-01-04",
    "Country": "US",
    "City": "Los Angeles",
    "Specie": "pm25",
    "count": 120,
    "min": 25,
    "max": 133,
    "median": 68,
    "variance": 4577.94
  },
  {
    "Date": "2020-01-05",
    "Country": "US",
    "City": "Los Angeles",
    "Specie": "pm25",
    "count": 120,
    "min": 24,
    "max": 124,
    "median": 61,
    "variance": 4646.95
  },
  {
    "Date": "2020-01-06",
    "Country": "US",
    "City": "Los Angeles",
    "Specie": "pm25",
    "count": 114,
    "min": 5,
    "max": 112,
    "median": 46,
    "variance": 6446.78
  },
  {
    "Date": "2020-01-07",
    "Country": "US",
    "City": "Los Angeles",
    "Specie": "pm25",
    "count": 116,
    "min": 9,
    "max": 59,
    "median": 25,
    "variance": 1919.22
  },
  {
    "Date": "2020-01-08",
    "Country": "US",
    "City": "Los Angeles",
    "Specie": "pm25",
    "count": 72,
    "min": 22,
    "max": 70,
    "median": 50,
    "variance": 1408.44
  },
  {
    "Date": "2020-01-09",
    "Country": "US",
    "City": "Los Angeles",
    "Specie": "pm25",
    "count": 66,
    "min": 8,
    "max": 68,
    "median": 42,
    "variance": 2675.49
  },
  {
    "Date": "2020-01-10",
    "Country": "US",
    "City": "Los Angeles",
    "Specie": "pm25",
    "count": 70,
    "min": 4,
    "max": 73,
    "median": 53,
    "variance": 3416.72
  },
  {
    "Date": "2020-01-11",
    "Country": "US",
    "City": "Los Angeles",
    "Specie": "pm25",
    "count": 72,
    "min": 10,
    "max": 93,
    "median": 61,
    "variance": 4966.29
  },
  {
    "Date": "2020-01-12",
    "Country": "US",
    "City": "Los Angeles",
    "Specie": "pm25",
    "count": 72,
    "min": 28,
    "max": 87,
    "median": 62,
    "variance": 2448.86
  },
  {
    "Date": "2020-01-13",
    "Country": "US",
    "City": "Los Angeles",
    "Specie": "pm25",
    "count": 72,
    "min": 30,
    "max": 97,
    "median": 63,
    "variance": 3617.31
  },
  {
    "Date": "2020-01-14",
    "Country": "US",
    "City": "Los Angeles",
    "Specie": "pm25",
    "count": 72,
    "min": 38,
    "max": 103,
    "median": 73,
    "variance": 2145.62
  },
  {
    "Date": "2020-01-15",
    "Country": "US",
    "City": "Los Angeles",
    "Specie": "pm25",
    "count": 72,
    "min": 55,
    "max": 152,
    "median": 94,
    "variance": 5173.73
  },
  {
    "Date": "2020-01-16",
    "Country": "US",
    "City": "Los Angeles",
    "Specie": "pm25",
    "count": 72,
    "min": 3,
    "max": 157,
    "median": 80,
    "variance": 29856
  },
  {
    "Date": "2020-01-17",
    "Country": "US",
    "City": "Los Angeles",
    "Specie": "pm25",
    "count": 72,
    "min": 9,
    "max": 66,
    "median": 30,
    "variance": 2122.25
  },
  {
    "Date": "2020-01-18",
    "Country": "US",
    "City": "Los Angeles",
    "Specie": "pm25",
    "count": 72,
    "min": 11,
    "max": 96,
    "median": 44,
    "variance": 5677.18
  },
  {
    "Date": "2020-01-19",
    "Country": "US",
    "City": "Los Angeles",
    "Specie": "pm25",
    "count": 72,
    "min": 5,
    "max": 103,
    "median": 50,
    "variance": 5850.92
  },
  {
    "Date": "2020-01-20",
    "Country": "US",
    "City": "Los Angeles",
    "Specie": "pm25",
    "count": 72,
    "min": 15,
    "max": 110,
    "median": 61,
    "variance": 5163.38
  },
  {
    "Date": "2020-01-21",
    "Country": "US",
    "City": "Los Angeles",
    "Specie": "pm25",
    "count": 72,
    "min": 8,
    "max": 59,
    "median": 34,
    "variance": 1510.7
  },
  {
    "Date": "2020-01-22",
    "Country": "US",
    "City": "Los Angeles",
    "Specie": "pm25",
    "count": 72,
    "min": 25,
    "max": 80,
    "median": 46,
    "variance": 2070.66
  },
  {
    "Date": "2020-01-23",
    "Country": "US",
    "City": "Los Angeles",
    "Specie": "pm25",
    "count": 72,
    "min": 17,
    "max": 86,
    "median": 57,
    "variance": 4098.97
  },
  {
    "Date": "2020-01-24",
    "Country": "US",
    "City": "Los Angeles",
    "Specie": "pm25",
    "count": 72,
    "min": 30,
    "max": 88,
    "median": 55,
    "variance": 2457.56
  },
  {
    "Date": "2020-01-25",
    "Country": "US",
    "City": "Los Angeles",
    "Specie": "pm25",
    "count": 72,
    "min": 38,
    "max": 143,
    "median": 72,
    "variance": 5799.76
  },
  {
    "Date": "2020-01-26",
    "Country": "US",
    "City": "Los Angeles",
    "Specie": "pm25",
    "count": 72,
    "min": 41,
    "max": 151,
    "median": 64,
    "variance": 9563
  },
  {
    "Date": "2020-01-27",
    "Country": "US",
    "City": "Los Angeles",
    "Specie": "pm25",
    "count": 72,
    "min": 23,
    "max": 119,
    "median": 76,
    "variance": 5256.05
  },
  {
    "Date": "2020-01-28",
    "Country": "US",
    "City": "Los Angeles",
    "Specie": "pm25",
    "count": 70,
    "min": 13,
    "max": 80,
    "median": 48,
    "variance": 3744.78
  },
  {
    "Date": "2020-01-29",
    "Country": "US",
    "City": "Los Angeles",
    "Specie": "pm25",
    "count": 70,
    "min": 9,
    "max": 76,
    "median": 42,
    "variance": 2198.23
  },
  {
    "Date": "2020-01-30",
    "Country": "US",
    "City": "Los Angeles",
    "Specie": "pm25",
    "count": 72,
    "min": 17,
    "max": 101,
    "median": 43,
    "variance": 3504.69
  },
  {
    "Date": "2020-01-31",
    "Country": "US",
    "City": "Los Angeles",
    "Specie": "pm25",
    "count": 68,
    "min": 6,
    "max": 84,
    "median": 46,
    "variance": 4776.2
  },
  {
    "Date": "2020-02-01",
    "Country": "US",
    "City": "Los Angeles",
    "Specie": "pm25",
    "count": 72,
    "min": 17,
    "max": 78,
    "median": 43,
    "variance": 3275.63
  },
  {
    "Date": "2020-02-02",
    "Country": "US",
    "City": "Los Angeles",
    "Specie": "pm25",
    "count": 72,
    "min": 17,
    "max": 99,
    "median": 57,
    "variance": 4792.27
  },
  {
    "Date": "2020-02-03",
    "Country": "US",
    "City": "Los Angeles",
    "Specie": "pm25",
    "count": 66,
    "min": 5,
    "max": 52,
    "median": 23,
    "variance": 1396.96
  },
  {
    "Date": "2020-02-04",
    "Country": "US",
    "City": "Los Angeles",
    "Specie": "pm25",
    "count": 72,
    "min": 4,
    "max": 53,
    "median": 26,
    "variance": 1762.52
  },
  {
    "Date": "2020-02-05",
    "Country": "US",
    "City": "Los Angeles",
    "Specie": "pm25",
    "count": 72,
    "min": 5,
    "max": 82,
    "median": 30,
    "variance": 4761.06
  },
  {
    "Date": "2020-02-06",
    "Country": "US",
    "City": "Los Angeles",
    "Specie": "pm25",
    "count": 66,
    "min": 15,
    "max": 72,
    "median": 52,
    "variance": 1576.22
  },
  {
    "Date": "2020-02-07",
    "Country": "US",
    "City": "Los Angeles",
    "Specie": "pm25",
    "count": 69,
    "min": 15,
    "max": 131,
    "median": 66,
    "variance": 4898.61
  },
  {
    "Date": "2020-02-08",
    "Country": "US",
    "City": "Los Angeles",
    "Specie": "pm25",
    "count": 68,
    "min": 34,
    "max": 121,
    "median": 71,
    "variance": 4964.14
  },
  {
    "Date": "2020-02-09",
    "Country": "US",
    "City": "Los Angeles",
    "Specie": "pm25",
    "count": 48,
    "min": 13,
    "max": 74,
    "median": 42,
    "variance": 2547.64
  },
  {
    "Date": "2020-02-10",
    "Country": "US",
    "City": "Los Angeles",
    "Specie": "pm25",
    "count": 47,
    "min": 13,
    "max": 69,
    "median": 38,
    "variance": 1635.84
  },
  {
    "Date": "2020-02-11",
    "Country": "US",
    "City": "Los Angeles",
    "Specie": "pm25",
    "count": 48,
    "min": 9,
    "max": 68,
    "median": 34,
    "variance": 1906.56
  },
  {
    "Date": "2020-02-12",
    "Country": "US",
    "City": "Los Angeles",
    "Specie": "pm25",
    "count": 48,
    "min": 30,
    "max": 72,
    "median": 46,
    "variance": 983.76
  },
  {
    "Date": "2020-02-13",
    "Country": "US",
    "City": "Los Angeles",
    "Specie": "pm25",
    "count": 48,
    "min": 25,
    "max": 113,
    "median": 57,
    "variance": 2227.16
  },
  {
    "Date": "2020-02-14",
    "Country": "US",
    "City": "Los Angeles",
    "Specie": "pm25",
    "count": 48,
    "min": 26,
    "max": 99,
    "median": 57,
    "variance": 2309.78
  },
  {
    "Date": "2020-02-15",
    "Country": "US",
    "City": "Los Angeles",
    "Specie": "pm25",
    "count": 48,
    "min": 36,
    "max": 106,
    "median": 63,
    "variance": 2052.32
  },
  {
    "Date": "2020-02-16",
    "Country": "US",
    "City": "Los Angeles",
    "Specie": "pm25",
    "count": 48,
    "min": 40,
    "max": 89,
    "median": 63,
    "variance": 1476.15
  },
  {
    "Date": "2020-02-17",
    "Country": "US",
    "City": "Los Angeles",
    "Specie": "pm25",
    "count": 48,
    "min": 45,
    "max": 108,
    "median": 67,
    "variance": 1795.95
  },
  {
    "Date": "2020-02-18",
    "Country": "US",
    "City": "Los Angeles",
    "Specie": "pm25",
    "count": 48,
    "min": 34,
    "max": 87,
    "median": 59,
    "variance": 1854.82
  },
  {
    "Date": "2020-02-19",
    "Country": "US",
    "City": "Los Angeles",
    "Specie": "pm25",
    "count": 47,
    "min": 47,
    "max": 97,
    "median": 70,
    "variance": 2073.02
  },
  {
    "Date": "2020-02-20",
    "Country": "US",
    "City": "Los Angeles",
    "Specie": "pm25",
    "count": 48,
    "min": 31,
    "max": 107,
    "median": 70,
    "variance": 3349.68
  },
  {
    "Date": "2020-02-21",
    "Country": "US",
    "City": "Los Angeles",
    "Specie": "pm25",
    "count": 48,
    "min": 21,
    "max": 111,
    "median": 53,
    "variance": 5008.83
  },
  {
    "Date": "2020-02-22",
    "Country": "US",
    "City": "Los Angeles",
    "Specie": "pm25",
    "count": 47,
    "min": 8,
    "max": 59,
    "median": 34,
    "variance": 863.76
  },
  {
    "Date": "2020-02-23",
    "Country": "US",
    "City": "Los Angeles",
    "Specie": "pm25",
    "count": 48,
    "min": 25,
    "max": 57,
    "median": 46,
    "variance": 784.04
  },
  {
    "Date": "2020-02-24",
    "Country": "US",
    "City": "Los Angeles",
    "Specie": "pm25",
    "count": 68,
    "min": 28,
    "max": 78,
    "median": 56,
    "variance": 843.17
  },
  {
    "Date": "2020-02-25",
    "Country": "US",
    "City": "Los Angeles",
    "Specie": "pm25",
    "count": 72,
    "min": 25,
    "max": 96,
    "median": 53,
    "variance": 2509.23
  },
  {
    "Date": "2020-02-26",
    "Country": "US",
    "City": "Los Angeles",
    "Specie": "pm25",
    "count": 69,
    "min": 1,
    "max": 74,
    "median": 50,
    "variance": 3033.7
  },
  {
    "Date": "2020-02-27",
    "Country": "US",
    "City": "Los Angeles",
    "Specie": "pm25",
    "count": 66,
    "min": 9,
    "max": 79,
    "median": 46,
    "variance": 3073.23
  },
  {
    "Date": "2020-02-28",
    "Country": "US",
    "City": "Los Angeles",
    "Specie": "pm25",
    "count": 72,
    "min": 8,
    "max": 78,
    "median": 34,
    "variance": 3649.01
  },
  {
    "Date": "2020-02-29",
    "Country": "US",
    "City": "Los Angeles",
    "Specie": "pm25",
    "count": 72,
    "min": 14,
    "max": 62,
    "median": 42,
    "variance": 1365.88
  },
  {
    "Date": "2020-03-01",
    "Country": "US",
    "City": "Los Angeles",
    "Specie": "pm25",
    "count": 72,
    "min": 4,
    "max": 55,
    "median": 38,
    "variance": 1333
  },
  {
    "Date": "2020-03-02",
    "Country": "US",
    "City": "Los Angeles",
    "Specie": "pm25",
    "count": 38,
    "min": 17,
    "max": 65,
    "median": 34,
    "variance": 1734.29
  },
  {
    "Date": "2020-03-03",
    "Country": "US",
    "City": "Los Angeles",
    "Specie": "pm25",
    "count": 50,
    "min": 5,
    "max": 68,
    "median": 32,
    "variance": 2831.84
  },
  {
    "Date": "2020-03-04",
    "Country": "US",
    "City": "Los Angeles",
    "Specie": "pm25",
    "count": 72,
    "min": 36,
    "max": 73,
    "median": 55,
    "variance": 604.69
  },
  {
    "Date": "2020-03-05",
    "Country": "US",
    "City": "Los Angeles",
    "Specie": "pm25",
    "count": 64,
    "min": 30,
    "max": 131,
    "median": 63,
    "variance": 4582.44
  },
  {
    "Date": "2020-03-06",
    "Country": "US",
    "City": "Los Angeles",
    "Specie": "pm25",
    "count": 72,
    "min": 18,
    "max": 102,
    "median": 54,
    "variance": 3497.96
  },
  {
    "Date": "2020-03-07",
    "Country": "US",
    "City": "Los Angeles",
    "Specie": "pm25",
    "count": 58,
    "min": 3,
    "max": 59,
    "median": 20,
    "variance": 1876.92
  },
  {
    "Date": "2020-03-08",
    "Country": "US",
    "City": "Los Angeles",
    "Specie": "pm25",
    "count": 66,
    "min": 2,
    "max": 49,
    "median": 17,
    "variance": 1433.53
  },
  {
    "Date": "2020-03-09",
    "Country": "US",
    "City": "Los Angeles",
    "Specie": "pm25",
    "count": 72,
    "min": 4,
    "max": 69,
    "median": 30,
    "variance": 1505.23
  },
  {
    "Date": "2020-03-10",
    "Country": "US",
    "City": "Los Angeles",
    "Specie": "pm25",
    "count": 72,
    "min": 1,
    "max": 37,
    "median": 17,
    "variance": 844.04
  },
  {
    "Date": "2020-03-11",
    "Country": "US",
    "City": "Los Angeles",
    "Specie": "pm25",
    "count": 68,
    "min": 5,
    "max": 42,
    "median": 20,
    "variance": 743.17
  },
  {
    "Date": "2020-03-12",
    "Country": "US",
    "City": "Los Angeles",
    "Specie": "pm25",
    "count": 72,
    "min": 6,
    "max": 60,
    "median": 29,
    "variance": 1987.13
  },
  {
    "Date": "2020-03-13",
    "Country": "US",
    "City": "Los Angeles",
    "Specie": "pm25",
    "count": 71,
    "min": 1,
    "max": 59,
    "median": 30,
    "variance": 1470.04
  },
  {
    "Date": "2020-03-14",
    "Country": "US",
    "City": "Los Angeles",
    "Specie": "pm25",
    "count": 68,
    "min": 4,
    "max": 50,
    "median": 18,
    "variance": 1343.56
  },
  {
    "Date": "2020-03-15",
    "Country": "US",
    "City": "Los Angeles",
    "Specie": "pm25",
    "count": 72,
    "min": 5,
    "max": 44,
    "median": 23,
    "variance": 1014.32
  },
  {
    "Date": "2020-03-16",
    "Country": "US",
    "City": "Los Angeles",
    "Specie": "pm25",
    "count": 66,
    "min": 8,
    "max": 53,
    "median": 30,
    "variance": 1276.16
  },
  {
    "Date": "2020-03-17",
    "Country": "US",
    "City": "Los Angeles",
    "Specie": "pm25",
    "count": 70,
    "min": 3,
    "max": 63,
    "median": 21,
    "variance": 1908.41
  },
  {
    "Date": "2020-03-18",
    "Country": "US",
    "City": "Los Angeles",
    "Specie": "pm25",
    "count": 72,
    "min": 2,
    "max": 69,
    "median": 30,
    "variance": 2683.85
  },
  {
    "Date": "2020-03-19",
    "Country": "US",
    "City": "Los Angeles",
    "Specie": "pm25",
    "count": 64,
    "min": 5,
    "max": 46,
    "median": 21,
    "variance": 1362.62
  },
  {
    "Date": "2020-03-20",
    "Country": "US",
    "City": "Los Angeles",
    "Specie": "pm25",
    "count": 62,
    "min": 1,
    "max": 57,
    "median": 25,
    "variance": 1758.65
  },
  {
    "Date": "2020-03-21",
    "Country": "US",
    "City": "Los Angeles",
    "Specie": "pm25",
    "count": 67,
    "min": 6,
    "max": 95,
    "median": 22,
    "variance": 2335.33
  },
  {
    "Date": "2020-03-22",
    "Country": "US",
    "City": "Los Angeles",
    "Specie": "pm25",
    "count": 66,
    "min": 2,
    "max": 52,
    "median": 26,
    "variance": 1885.58
  },
  {
    "Date": "2020-03-23",
    "Country": "US",
    "City": "Los Angeles",
    "Specie": "pm25",
    "count": 60,
    "min": 4,
    "max": 37,
    "median": 14,
    "variance": 601.31
  },
  {
    "Date": "2020-03-24",
    "Country": "US",
    "City": "Los Angeles",
    "Specie": "pm25",
    "count": 68,
    "min": 9,
    "max": 40,
    "median": 25,
    "variance": 665.19
  },
  {
    "Date": "2020-03-25",
    "Country": "US",
    "City": "Los Angeles",
    "Specie": "pm25",
    "count": 63,
    "min": 1,
    "max": 39,
    "median": 14,
    "variance": 767.23
  },
  {
    "Date": "2020-03-26",
    "Country": "US",
    "City": "Los Angeles",
    "Specie": "pm25",
    "count": 68,
    "min": 5,
    "max": 64,
    "median": 17,
    "variance": 1360.01
  },
  {
    "Date": "2020-03-27",
    "Country": "US",
    "City": "Los Angeles",
    "Specie": "pm25",
    "count": 70,
    "min": 3,
    "max": 51,
    "median": 26,
    "variance": 1168.78
  },
  {
    "Date": "2020-03-28",
    "Country": "US",
    "City": "Los Angeles",
    "Specie": "pm25",
    "count": 72,
    "min": 17,
    "max": 53,
    "median": 35,
    "variance": 823.56
  },
  {
    "Date": "2020-03-29",
    "Country": "US",
    "City": "Los Angeles",
    "Specie": "pm25",
    "count": 69,
    "min": 12,
    "max": 63,
    "median": 42,
    "variance": 1596.32
  },
  {
    "Date": "2020-03-30",
    "Country": "US",
    "City": "Los Angeles",
    "Specie": "pm25",
    "count": 71,
    "min": 8,
    "max": 53,
    "median": 39,
    "variance": 1126.99
  },
  {
    "Date": "2020-03-30",
    "Country": "US",
    "City": "Los Angeles",
    "Specie": "pm25",
    "count": 71,
    "min": 8,
    "max": 53,
    "median": 39,
    "variance": 1126.99
  },
  {
    "Date": "2020-03-31",
    "Country": "US",
    "City": "Los Angeles",
    "Specie": "pm25",
    "count": 71,
    "min": 25,
    "max": 72,
    "median": 42,
    "variance": 1311.52
  },
  {
    "Date": "2020-03-31",
    "Country": "US",
    "City": "Los Angeles",
    "Specie": "pm25",
    "count": 71,
    "min": 25,
    "max": 72,
    "median": 42,
    "variance": 1311.52
  },
  {
    "Date": "2020-04-01",
    "Country": "US",
    "City": "Los Angeles",
    "Specie": "pm25",
    "count": 72,
    "min": 20,
    "max": 61,
    "median": 39,
    "variance": 1020.4
  },
  {
    "Date": "2020-04-01",
    "Country": "US",
    "City": "Los Angeles",
    "Specie": "pm25",
    "count": 72,
    "min": 20,
    "max": 61,
    "median": 39,
    "variance": 1020.4
  },
  {
    "Date": "2020-04-02",
    "Country": "US",
    "City": "Los Angeles",
    "Specie": "pm25",
    "count": 72,
    "min": 23,
    "max": 57,
    "median": 46,
    "variance": 542.75
  },
  {
    "Date": "2020-04-02",
    "Country": "US",
    "City": "Los Angeles",
    "Specie": "pm25",
    "count": 72,
    "min": 23,
    "max": 57,
    "median": 46,
    "variance": 542.75
  },
  {
    "Date": "2020-04-03",
    "Country": "US",
    "City": "Los Angeles",
    "Specie": "pm25",
    "count": 57,
    "min": 26,
    "max": 66,
    "median": 45,
    "variance": 869.62
  },
  {
    "Date": "2020-04-03",
    "Country": "US",
    "City": "Los Angeles",
    "Specie": "pm25",
    "count": 57,
    "min": 26,
    "max": 66,
    "median": 45,
    "variance": 869.62
  },
  {
    "Date": "2020-04-04",
    "Country": "US",
    "City": "Los Angeles",
    "Specie": "pm25",
    "count": 48,
    "min": 25,
    "max": 57,
    "median": 42,
    "variance": 597.43
  },
  {
    "Date": "2020-04-04",
    "Country": "US",
    "City": "Los Angeles",
    "Specie": "pm25",
    "count": 48,
    "min": 25,
    "max": 57,
    "median": 42,
    "variance": 597.43
  },
  {
    "Date": "2020-04-05",
    "Country": "US",
    "City": "Los Angeles",
    "Specie": "pm25",
    "count": 38,
    "min": 1,
    "max": 37,
    "median": 17,
    "variance": 1289.56
  },
  {
    "Date": "2020-04-05",
    "Country": "US",
    "City": "Los Angeles",
    "Specie": "pm25",
    "count": 38,
    "min": 1,
    "max": 37,
    "median": 17,
    "variance": 1289.56
  },
  {
    "Date": "2020-04-06",
    "Country": "US",
    "City": "Los Angeles",
    "Specie": "pm25",
    "count": 46,
    "min": 3,
    "max": 24,
    "median": 12,
    "variance": 290.43
  },
  {
    "Date": "2020-04-07",
    "Country": "US",
    "City": "Los Angeles",
    "Specie": "pm25",
    "count": 53,
    "min": 3,
    "max": 47,
    "median": 17,
    "variance": 1266.01
  },
  {
    "Date": "2020-04-08",
    "Country": "US",
    "City": "Los Angeles",
    "Specie": "pm25",
    "count": 63,
    "min": 5,
    "max": 55,
    "median": 22,
    "variance": 1489.93
  },
  {
    "Date": "2020-04-09",
    "Country": "US",
    "City": "Los Angeles",
    "Specie": "pm25",
    "count": 65,
    "min": 5,
    "max": 41,
    "median": 17,
    "variance": 948.4
  },
  {
    "Date": "2020-04-10",
    "Country": "US",
    "City": "Los Angeles",
    "Specie": "pm25",
    "count": 57,
    "min": 1,
    "max": 51,
    "median": 10,
    "variance": 2220.89
  },
  {
    "Date": "2020-04-11",
    "Country": "US",
    "City": "Los Angeles",
    "Specie": "pm25",
    "count": 70,
    "min": 6,
    "max": 42,
    "median": 29,
    "variance": 855.99
  },
  {
    "Date": "2020-04-12",
    "Country": "US",
    "City": "Los Angeles",
    "Specie": "pm25",
    "count": 68,
    "min": 5,
    "max": 50,
    "median": 29,
    "variance": 1428.51
  },
  {
    "Date": "2020-04-13",
    "Country": "US",
    "City": "Los Angeles",
    "Specie": "pm25",
    "count": 72,
    "min": 5,
    "max": 36,
    "median": 22,
    "variance": 781.62
  },
  {
    "Date": "2020-04-14",
    "Country": "US",
    "City": "Los Angeles",
    "Specie": "pm25",
    "count": 71,
    "min": 13,
    "max": 60,
    "median": 41,
    "variance": 1095.35
  },
  {
    "Date": "2020-04-15",
    "Country": "US",
    "City": "Los Angeles",
    "Specie": "pm25",
    "count": 66,
    "min": 21,
    "max": 74,
    "median": 44,
    "variance": 2475.01
  },
  {
    "Date": "2020-04-16",
    "Country": "US",
    "City": "Los Angeles",
    "Specie": "pm25",
    "count": 72,
    "min": 25,
    "max": 68,
    "median": 44,
    "variance": 1068.91
  },
  {
    "Date": "2020-04-17",
    "Country": "US",
    "City": "Los Angeles",
    "Specie": "pm25",
    "count": 41,
    "min": 5,
    "max": 53,
    "median": 38,
    "variance": 1314.51
  },
  {
    "Date": "2020-04-18",
    "Country": "US",
    "City": "Los Angeles",
    "Specie": "pm25",
    "count": 16,
    "min": 13,
    "max": 30,
    "median": 21,
    "variance": 289.62
  },
  {
    "Date": "2020-04-19",
    "Country": "US",
    "City": "Los Angeles",
    "Specie": "pm25",
    "count": 23,
    "min": 5,
    "max": 30,
    "median": 21,
    "variance": 339.88
  },
  {
    "Date": "2020-04-20",
    "Country": "US",
    "City": "Los Angeles",
    "Specie": "pm25",
    "count": 22,
    "min": 17,
    "max": 46,
    "median": 30,
    "variance": 784.18
  },
  {
    "Date": "2020-04-21",
    "Country": "US",
    "City": "Los Angeles",
    "Specie": "pm25",
    "count": 48,
    "min": 17,
    "max": 55,
    "median": 34,
    "variance": 1382.11
  },
  {
    "Date": "2020-04-22",
    "Country": "US",
    "City": "Los Angeles",
    "Specie": "pm25",
    "count": 72,
    "min": 9,
    "max": 64,
    "median": 50,
    "variance": 1308.29
  },
  {
    "Date": "2020-04-23",
    "Country": "US",
    "City": "Los Angeles",
    "Specie": "pm25",
    "count": 72,
    "min": 25,
    "max": 74,
    "median": 46,
    "variance": 1596.32
  },
  {
    "Date": "2020-04-24",
    "Country": "US",
    "City": "Los Angeles",
    "Specie": "pm25",
    "count": 40,
    "min": 24,
    "max": 68,
    "median": 41,
    "variance": 1684.35
  },
  {
    "Date": "2020-04-25",
    "Country": "US",
    "City": "Los Angeles",
    "Specie": "pm25",
    "count": 23,
    "min": 38,
    "max": 65,
    "median": 57,
    "variance": 418.97
  },
  {
    "Date": "2020-04-26",
    "Country": "US",
    "City": "Los Angeles",
    "Specie": "pm25",
    "count": 21,
    "min": 46,
    "max": 70,
    "median": 61,
    "variance": 359.48
  },
  {
    "Date": "2020-04-27",
    "Country": "US",
    "City": "Los Angeles",
    "Specie": "pm25",
    "count": 24,
    "min": 50,
    "max": 70,
    "median": 59,
    "variance": 249.4
  },
  {
    "Date": "2020-04-28",
    "Country": "US",
    "City": "Los Angeles",
    "Specie": "pm25",
    "count": 50,
    "min": 47,
    "max": 87,
    "median": 56,
    "variance": 734.54
  },
  {
    "Date": "2020-04-29",
    "Country": "US",
    "City": "Los Angeles",
    "Specie": "pm25",
    "count": 72,
    "min": 35,
    "max": 107,
    "median": 52,
    "variance": 2217.31
  },
  {
    "Date": "2020-04-30",
    "Country": "US",
    "City": "Los Angeles",
    "Specie": "pm25",
    "count": 72,
    "min": 25,
    "max": 87,
    "median": 61,
    "variance": 2274.05
  },
  {
    "Date": "2020-05-01",
    "Country": "US",
    "City": "Los Angeles",
    "Specie": "pm25",
    "count": 72,
    "min": 38,
    "max": 74,
    "median": 51,
    "variance": 808.64
  },
  {
    "Date": "2020-05-02",
    "Country": "US",
    "City": "Los Angeles",
    "Specie": "pm25",
    "count": 72,
    "min": 3,
    "max": 65,
    "median": 43,
    "variance": 2403.66
  },
  {
    "Date": "2020-05-03",
    "Country": "US",
    "City": "Los Angeles",
    "Specie": "pm25",
    "count": 72,
    "min": 13,
    "max": 61,
    "median": 44,
    "variance": 1220.84
  },
  {
    "Date": "2020-05-04",
    "Country": "US",
    "City": "Los Angeles",
    "Specie": "pm25",
    "count": 72,
    "min": 40,
    "max": 72,
    "median": 52,
    "variance": 490.97
  },
  {
    "Date": "2020-05-05",
    "Country": "US",
    "City": "Los Angeles",
    "Specie": "pm25",
    "count": 72,
    "min": 30,
    "max": 81,
    "median": 55,
    "variance": 1234.6
  },
  {
    "Date": "2020-05-06",
    "Country": "US",
    "City": "Los Angeles",
    "Specie": "pm25",
    "count": 72,
    "min": 25,
    "max": 80,
    "median": 57,
    "variance": 1585.16
  },
  {
    "Date": "2020-05-07",
    "Country": "US",
    "City": "Los Angeles",
    "Specie": "pm25",
    "count": 71,
    "min": 36,
    "max": 82,
    "median": 58,
    "variance": 838.76
  },
  {
    "Date": "2020-05-08",
    "Country": "US",
    "City": "Los Angeles",
    "Specie": "pm25",
    "count": 63,
    "min": 42,
    "max": 93,
    "median": 61,
    "variance": 1478.06
  },
  {
    "Date": "2020-05-09",
    "Country": "US",
    "City": "Los Angeles",
    "Specie": "pm25",
    "count": 71,
    "min": 52,
    "max": 95,
    "median": 65,
    "variance": 999
  },
  {
    "Date": "2020-05-10",
    "Country": "US",
    "City": "Los Angeles",
    "Specie": "pm25",
    "count": 70,
    "min": 34,
    "max": 72,
    "median": 54,
    "variance": 641.07
  },
  {
    "Date": "2020-05-11",
    "Country": "US",
    "City": "Los Angeles",
    "Specie": "pm25",
    "count": 72,
    "min": 25,
    "max": 55,
    "median": 45,
    "variance": 664.12
  },
  {
    "Date": "2020-05-12",
    "Country": "US",
    "City": "Los Angeles",
    "Specie": "pm25",
    "count": 68,
    "min": 8,
    "max": 51,
    "median": 32,
    "variance": 1451.44
  },
  {
    "Date": "2020-05-13",
    "Country": "US",
    "City": "Los Angeles",
    "Specie": "pm25",
    "count": 69,
    "min": 8,
    "max": 55,
    "median": 29,
    "variance": 1399.5
  },
  {
    "Date": "2020-05-14",
    "Country": "US",
    "City": "Los Angeles",
    "Specie": "pm25",
    "count": 72,
    "min": 17,
    "max": 65,
    "median": 41,
    "variance": 1269.28
  },
  {
    "Date": "2020-05-15",
    "Country": "US",
    "City": "Los Angeles",
    "Specie": "pm25",
    "count": 72,
    "min": 27,
    "max": 71,
    "median": 41,
    "variance": 775.99
  },
  {
    "Date": "2020-05-16",
    "Country": "US",
    "City": "Los Angeles",
    "Specie": "pm25",
    "count": 70,
    "min": 21,
    "max": 63,
    "median": 45,
    "variance": 875.41
  },
  {
    "Date": "2020-05-17",
    "Country": "US",
    "City": "Los Angeles",
    "Specie": "pm25",
    "count": 72,
    "min": 10,
    "max": 62,
    "median": 46,
    "variance": 2247.02
  },
  {
    "Date": "2020-05-18",
    "Country": "US",
    "City": "Los Angeles",
    "Specie": "pm25",
    "count": 65,
    "min": 3,
    "max": 35,
    "median": 15,
    "variance": 569.53
  },
  {
    "Date": "2020-05-19",
    "Country": "US",
    "City": "Los Angeles",
    "Specie": "pm25",
    "count": 69,
    "min": 2,
    "max": 60,
    "median": 28,
    "variance": 1202.43
  },
  {
    "Date": "2020-05-20",
    "Country": "US",
    "City": "Los Angeles",
    "Specie": "pm25",
    "count": 72,
    "min": 9,
    "max": 65,
    "median": 34,
    "variance": 1244.15
  },
  {
    "Date": "2020-05-21",
    "Country": "US",
    "City": "Los Angeles",
    "Specie": "pm25",
    "count": 72,
    "min": 27,
    "max": 79,
    "median": 48,
    "variance": 1357.79
  },
  {
    "Date": "2020-05-22",
    "Country": "US",
    "City": "Los Angeles",
    "Specie": "pm25",
    "count": 71,
    "min": 25,
    "max": 63,
    "median": 53,
    "variance": 718.03
  },
  {
    "Date": "2020-05-23",
    "Country": "US",
    "City": "Los Angeles",
    "Specie": "pm25",
    "count": 72,
    "min": 30,
    "max": 70,
    "median": 52,
    "variance": 529.9
  },
  {
    "Date": "2020-05-24",
    "Country": "US",
    "City": "Los Angeles",
    "Specie": "pm25",
    "count": 72,
    "min": 42,
    "max": 77,
    "median": 61,
    "variance": 347.37
  },
  {
    "Date": "2020-05-25",
    "Country": "US",
    "City": "Los Angeles",
    "Specie": "pm25",
    "count": 72,
    "min": 42,
    "max": 89,
    "median": 62,
    "variance": 1066.2
  },
  {
    "Date": "2020-05-26",
    "Country": "US",
    "City": "Los Angeles",
    "Specie": "pm25",
    "count": 72,
    "min": 30,
    "max": 90,
    "median": 57,
    "variance": 1219.42
  },
  {
    "Date": "2020-05-27",
    "Country": "US",
    "City": "Los Angeles",
    "Specie": "pm25",
    "count": 72,
    "min": 26,
    "max": 89,
    "median": 53,
    "variance": 2607.1
  },
  {
    "Date": "2020-05-28",
    "Country": "US",
    "City": "Los Angeles",
    "Specie": "pm25",
    "count": 71,
    "min": 9,
    "max": 71,
    "median": 46,
    "variance": 3350.04
  },
  {
    "Date": "2020-05-29",
    "Country": "US",
    "City": "Los Angeles",
    "Specie": "pm25",
    "count": 68,
    "min": 2,
    "max": 61,
    "median": 20,
    "variance": 2318.06
  },
  {
    "Date": "2020-05-30",
    "Country": "US",
    "City": "Los Angeles",
    "Specie": "pm25",
    "count": 71,
    "min": 9,
    "max": 67,
    "median": 25,
    "variance": 1783.42
  },
  {
    "Date": "2020-05-31",
    "Country": "US",
    "City": "Los Angeles",
    "Specie": "pm25",
    "count": 72,
    "min": 13,
    "max": 73,
    "median": 34,
    "variance": 1149.57
  },
  {
    "Date": "2020-06-01",
    "Country": "US",
    "City": "Los Angeles",
    "Specie": "pm25",
    "count": 72,
    "min": 21,
    "max": 73,
    "median": 40,
    "variance": 1250.8
  },
  {
    "Date": "2020-06-02",
    "Country": "US",
    "City": "Los Angeles",
    "Specie": "pm25",
    "count": 72,
    "min": 28,
    "max": 72,
    "median": 53,
    "variance": 934.83
  },
  {
    "Date": "2020-06-03",
    "Country": "US",
    "City": "Los Angeles",
    "Specie": "pm25",
    "count": 70,
    "min": 46,
    "max": 76,
    "median": 57,
    "variance": 542.71
  },
  {
    "Date": "2020-06-04",
    "Country": "US",
    "City": "Los Angeles",
    "Specie": "pm25",
    "count": 72,
    "min": 30,
    "max": 68,
    "median": 54,
    "variance": 750.05
  },
  {
    "Date": "2020-06-05",
    "Country": "US",
    "City": "Los Angeles",
    "Specie": "pm25",
    "count": 72,
    "min": 13,
    "max": 46,
    "median": 32,
    "variance": 496.57
  },
  {
    "Date": "2020-06-06",
    "Country": "US",
    "City": "Los Angeles",
    "Specie": "pm25",
    "count": 70,
    "min": 15,
    "max": 48,
    "median": 31,
    "variance": 759.84
  },
  {
    "Date": "2020-06-07",
    "Country": "US",
    "City": "Los Angeles",
    "Specie": "pm25",
    "count": 71,
    "min": 13,
    "max": 61,
    "median": 41,
    "variance": 1008.12
  },
  {
    "Date": "2020-06-08",
    "Country": "US",
    "City": "Los Angeles",
    "Specie": "pm25",
    "count": 66,
    "min": 5,
    "max": 67,
    "median": 30,
    "variance": 2024.78
  },
  {
    "Date": "2020-06-09",
    "Country": "US",
    "City": "Los Angeles",
    "Specie": "pm25",
    "count": 70,
    "min": 5,
    "max": 61,
    "median": 25,
    "variance": 3083.1
  },
  {
    "Date": "2020-06-10",
    "Country": "US",
    "City": "Los Angeles",
    "Specie": "pm25",
    "count": 71,
    "min": 17,
    "max": 71,
    "median": 43,
    "variance": 2246.09
  },
  {
    "Date": "2020-06-11",
    "Country": "US",
    "City": "Los Angeles",
    "Specie": "pm25",
    "count": 72,
    "min": 25,
    "max": 68,
    "median": 46,
    "variance": 1238.8
  },
  {
    "Date": "2020-06-12",
    "Country": "US",
    "City": "Los Angeles",
    "Specie": "pm25",
    "count": 72,
    "min": 21,
    "max": 61,
    "median": 42,
    "variance": 724.55
  },
  {
    "Date": "2020-06-13",
    "Country": "US",
    "City": "Los Angeles",
    "Specie": "pm25",
    "count": 36,
    "min": 17,
    "max": 55,
    "median": 42,
    "variance": 1004.09
  },
  {
    "Date": "2020-06-14",
    "Country": "US",
    "City": "Los Angeles",
    "Specie": "pm25",
    "count": 24,
    "min": 13,
    "max": 61,
    "median": 38,
    "variance": 1125.2
  },
  {
    "Date": "2020-06-15",
    "Country": "US",
    "City": "Los Angeles",
    "Specie": "pm25",
    "count": 24,
    "min": 30,
    "max": 61,
    "median": 42,
    "variance": 890.15
  },
  {
    "Date": "2020-06-16",
    "Country": "US",
    "City": "Los Angeles",
    "Specie": "pm25",
    "count": 44,
    "min": 12,
    "max": 65,
    "median": 40,
    "variance": 2026.64
  },
  {
    "Date": "2020-06-17",
    "Country": "US",
    "City": "Los Angeles",
    "Specie": "pm25",
    "count": 72,
    "min": 18,
    "max": 61,
    "median": 42,
    "variance": 631.27
  },
  {
    "Date": "2020-06-18",
    "Country": "US",
    "City": "Los Angeles",
    "Specie": "pm25",
    "count": 66,
    "min": 26,
    "max": 62,
    "median": 43,
    "variance": 647.54
  },
  {
    "Date": "2020-06-19",
    "Country": "US",
    "City": "Los Angeles",
    "Specie": "pm25",
    "count": 72,
    "min": 14,
    "max": 69,
    "median": 45,
    "variance": 1167.02
  },
  {
    "Date": "2020-06-20",
    "Country": "US",
    "City": "Los Angeles",
    "Specie": "pm25",
    "count": 60,
    "min": 17,
    "max": 64,
    "median": 49,
    "variance": 1039.49
  },
  {
    "Date": "2020-06-21",
    "Country": "US",
    "City": "Los Angeles",
    "Specie": "pm25",
    "count": 44,
    "min": 21,
    "max": 65,
    "median": 49,
    "variance": 779.94
  },
  {
    "Date": "2020-06-22",
    "Country": "US",
    "City": "Los Angeles",
    "Specie": "pm25",
    "count": 36,
    "min": 21,
    "max": 76,
    "median": 49,
    "variance": 1848.09
  },
  {
    "Date": "2020-06-23",
    "Country": "US",
    "City": "Los Angeles",
    "Specie": "pm25",
    "count": 64,
    "min": 25,
    "max": 91,
    "median": 46,
    "variance": 1837.21
  },
  {
    "Date": "2020-06-24",
    "Country": "US",
    "City": "Los Angeles",
    "Specie": "pm25",
    "count": 66,
    "min": 15,
    "max": 91,
    "median": 46,
    "variance": 3010.19
  },
  {
    "Date": "2020-06-25",
    "Country": "US",
    "City": "Los Angeles",
    "Specie": "pm25",
    "count": 72,
    "min": 3,
    "max": 65,
    "median": 32,
    "variance": 2226.85
  },
  {
    "Date": "2020-06-26",
    "Country": "US",
    "City": "Los Angeles",
    "Specie": "pm25",
    "count": 72,
    "min": 17,
    "max": 79,
    "median": 42,
    "variance": 2558.87
  },
  {
    "Date": "2020-06-27",
    "Country": "US",
    "City": "Los Angeles",
    "Specie": "pm25",
    "count": 72,
    "min": 22,
    "max": 82,
    "median": 42,
    "variance": 2015.09
  },
  {
    "Date": "2020-06-28",
    "Country": "US",
    "City": "Los Angeles",
    "Specie": "pm25",
    "count": 70,
    "min": 4,
    "max": 46,
    "median": 15,
    "variance": 1229.66
  },
  {
    "Date": "2020-06-29",
    "Country": "US",
    "City": "Los Angeles",
    "Specie": "pm25",
    "count": 68,
    "min": 4,
    "max": 57,
    "median": 31,
    "variance": 1472.27
  },
  {
    "Date": "2020-06-30",
    "Country": "US",
    "City": "Los Angeles",
    "Specie": "pm25",
    "count": 72,
    "min": 17,
    "max": 71,
    "median": 42,
    "variance": 1313.19
  },
  {
    "Date": "2020-07-01",
    "Country": "US",
    "City": "Los Angeles",
    "Specie": "pm25",
    "count": 72,
    "min": 18,
    "max": 65,
    "median": 42,
    "variance": 1347.7
  },
  {
    "Date": "2020-07-02",
    "Country": "US",
    "City": "Los Angeles",
    "Specie": "pm25",
    "count": 69,
    "min": 23,
    "max": 67,
    "median": 46,
    "variance": 1094.85
  },
  {
    "Date": "2020-07-03",
    "Country": "US",
    "City": "Los Angeles",
    "Specie": "pm25",
    "count": 72,
    "min": 24,
    "max": 76,
    "median": 46,
    "variance": 1576.83
  },
  {
    "Date": "2020-07-04",
    "Country": "US",
    "City": "Los Angeles",
    "Specie": "pm25",
    "count": 72,
    "min": 25,
    "max": 506,
    "median": 55,
    "variance": 102073
  },
  {
    "Date": "2020-07-05",
    "Country": "US",
    "City": "Los Angeles",
    "Specie": "pm25",
    "count": 69,
    "min": 29,
    "max": 528,
    "median": 66,
    "variance": 94197.1
  }
]